LICENSE
MANIFEST.in
README.md
requirements.txt
setup.py
bloxberg_cert_schema.egg-info/PKG-INFO
bloxberg_cert_schema.egg-info/SOURCES.txt
bloxberg_cert_schema.egg-info/dependency_links.txt
bloxberg_cert_schema.egg-info/requires.txt
bloxberg_cert_schema.egg-info/top_level.txt
cert_schema/__init__.py
cert_schema/errors.py
cert_schema/jsonld_helpers.py
cert_schema/schema_validator.py
cert_schema/1.1/certificate-schema-v1-1.json
cert_schema/1.1/issuer-schema-v1-1.json
cert_schema/1.2/assertion-1.2.json
cert_schema/1.2/blockchain-certificate-1.2.json
cert_schema/1.2/blockchain-receipt-1.2.json
cert_schema/1.2/certificate-1.2.json
cert_schema/1.2/certificate-document-1.2.json
cert_schema/1.2/context.json
cert_schema/1.2/issuer-1.2.json
cert_schema/1.2/issuer-id-1.2.json
cert_schema/2.0/context.json
cert_schema/2.0/issuerSchema.json
cert_schema/2.0/merkleProof2017Schema.json
cert_schema/2.0/obi.json
cert_schema/2.0/recipientSchema.json
cert_schema/2.0/schema.json
cert_schema/2.0/signatureLineSchema.json
cert_schema/2.0-alpha/context.json
cert_schema/2.0-alpha/issuerSchema.json
cert_schema/2.0-alpha/merkleProof2017Schema.json
cert_schema/2.0-alpha/recipientSchema.json
cert_schema/2.0-alpha/schema.json
cert_schema/2.0-alpha/signatureLineSchema.json
cert_schema/2.1/context.json
cert_schema/2.1/issuerSchema.json
cert_schema/2.1/merkleProof2017Schema.json
cert_schema/2.1/obi.json
cert_schema/2.1/recipientSchema.json
cert_schema/2.1/schema.json
cert_schema/2.1/signatureLineSchema.json
cert_schema/3.0-alpha/context.json
cert_schema/3.0-alpha/credential.json
cert_schema/3.0-alpha/exampleCredential.json
cert_schema/3.0-alpha/issuerSchema.json
cert_schema/3.0-alpha/merkleProof2019Context.json
cert_schema/3.0-alpha/merkleProof2019Schema.json
cert_schema/3.0-alpha/schema.json
cert_schema/bloxberg/context.json
cert_schema/bloxberg/credential.json
cert_schema/bloxberg/exampleCredential.json
cert_schema/bloxberg/issuerSchema.json
cert_schema/bloxberg/merkleProof2019Context.json
cert_schema/bloxberg/merkleProof2019Schema.json
cert_schema/bloxberg/schema.json
tests/__init__.py
tests/test_jsonld_helpers.py
tests/test_schema_validator.py