Metadata-Version: 2.1
Name: bloxberg-cert-schema
Version: 0.0.4
Summary: Blockchain certificates JSON-LD context and JSON schemas
Home-page: https://github.com/bloxberg-org/cert-schema
Author: info@bloxberg.org
Author-email: info@bloxberg.org
License: MIT
Platform: UNKNOWN
